<annotation>
	<folder>Armyworms</folder>
	<filename>39.jpg</filename>
	<path>C:\Users\Radhe Raman Tiwari\Pictures\ObjectDetection\Data\Armyworms\39.jpg</path>
	<source>
		<database>Unknown</database>
	</source>
	<size>
		<width>800</width>
		<height>600</height>
		<depth>3</depth>
	</size>
	<segmented>0</segmented>
	<object>
		<name>Armyworms</name>
		<pose>Unspecified</pose>
		<truncated>0</truncated>
		<difficult>0</difficult>
		<bndbox>
			<xmin>114</xmin>
			<ymin>235</ymin>
			<xmax>637</xmax>
			<ymax>357</ymax>
		</bndbox>
	</object>
</annotation>
