<annotation>
	<folder>Leaf_folder</folder>
	<filename>261.jpg</filename>
	<path>C:\Users\Radhe Raman Tiwari\Pictures\ObjectDetection\Data\Leaf_folder\261.jpg</path>
	<source>
		<database>Unknown</database>
	</source>
	<size>
		<width>800</width>
		<height>600</height>
		<depth>3</depth>
	</size>
	<segmented>0</segmented>
	<object>
		<name>Leaf_folder</name>
		<pose>Unspecified</pose>
		<truncated>0</truncated>
		<difficult>0</difficult>
		<bndbox>
			<xmin>355</xmin>
			<ymin>51</ymin>
			<xmax>419</xmax>
			<ymax>249</ymax>
		</bndbox>
	</object>
	<object>
		<name>Leaf_folder</name>
		<pose>Unspecified</pose>
		<truncated>0</truncated>
		<difficult>0</difficult>
		<bndbox>
			<xmin>372</xmin>
			<ymin>313</ymin>
			<xmax>490</xmax>
			<ymax>497</ymax>
		</bndbox>
	</object>
</annotation>
